[
  {
    "children": [
      {
        "children": [
          {
            "children": [
              {
                "children": [
                  {
                    "name": "searchBooks",
                    "type": "function",
                    "static": false,
                    "location": "src/main/java/com/miniproject/two/Library.java:152"
                  }
                ],
                "name": "Library",
                "type": "class"
              },
              {
                "children": [
                  {
                    "name": "testSearchBooks",
                    "type": "function",
                    "static": false,
                    "location": "src/test/java/com/miniproject/two/LibraryTest.java:39"
                  }
                ],
                "name": "LibraryTest",
                "type": "class"
              }
            ],
            "name": "two",
            "type": "package"
          }
        ],
        "name": "miniproject",
        "type": "package"
      }
    ],
    "name": "com",
    "type": "package"
  }
]